takeoff/__init__.py
takeoff/generator.py
takeoff/generators/__init__.py
takeoff/generators/android_generator.py
takeoff/generators/api_generator.py
takeoff/generators/generator_base.py
takeoff/generators/ios_generator.py
takeoff/generators/react_generator.py
takeoff/generators/web_generator.py
takeoff/generators/web/__init__.py
takeoff/generators/web/web_authentication_generator.py
takeoff/generators/web/web_base_generator.py
takeoff/generators/web/web_model_generator.py
takeoff/generators/web/web_project_generator.py
takeoff/generators/web/web_resource_generator.py
takeoff_pkg/__init__.py
takeoff_py-0.0.5.data/scripts/takeoff-generate
tests/__init__.py
takeoff_py-0.0.5.dist-info/LICENSE
takeoff_py-0.0.5.dist-info/METADATA
takeoff_py-0.0.5.dist-info/WHEEL
takeoff_py-0.0.5.dist-info/top_level.txt
takeoff_py-0.0.5.dist-info/RECORD
