Metadata-Version: 2.1
Name: takeoff-py
Version: 0.0.5
Summary: A Python toolset to launch full stack, mobile projects
Home-page: https://github.com/themarceloribeiro/takeoff-py
Author: Marcelo Ribeiro
Author-email: themarceloribeiro@gmail.com
License: UNKNOWN
Platform: UNKNOWN
Classifier: Programming Language :: Python :: 3
Classifier: License :: OSI Approved :: MIT License
Classifier: Operating System :: OS Independent
Requires-Python: >=3.6
Requires-Dist: jinja2
Requires-Dist: django-bootstrap4
Requires-Dist: nose
